x_mlps/__init__.py
x_mlps/_ff.py
x_mlps/_nn.py
x_mlps/_types.py
x_mlps/_utils.py
x_mlps/_version.py
x_mlps/_x_mlps.py
x_mlps-0.5.0.dist-info/LICENSE
x_mlps-0.5.0.dist-info/WHEEL
x_mlps-0.5.0.dist-info/METADATA
x_mlps-0.5.0.dist-info/RECORD
