Metadata-Version: 2.1
Name: x-mlps
Version: 0.5.0
Summary: Configurable MLPs built on JAX and Haiku
Home-page: https://github.com/PyriteAI/x-mlps
License: MIT
Keywords: artificial intelligence,machine learning,jax,haiku,multilayer perceptron
Author: Miller Wilt
Author-email: miller@pyriteai.com
Requires-Python: >=3.8,<4.0
Classifier: Development Status :: 4 - Beta
Classifier: Intended Audience :: Developers
Classifier: License :: OSI Approved :: MIT License
Classifier: Programming Language :: Python :: 3
Classifier: Programming Language :: Python :: 3.10
Classifier: Programming Language :: Python :: 3.8
Classifier: Programming Language :: Python :: 3.9
Classifier: Topic :: Scientific/Engineering :: Artificial Intelligence
Classifier: Typing :: Typed
Requires-Dist: dm-haiku (>=0.0.6,<0.0.7)
Requires-Dist: einops (>=0.4.1,<0.5.0)
Project-URL: Repository, https://github.com/PyriteAI/x-mlps
